hydra/__init__.py
hydra/column.py
hydra/connection.py
hydra/database.py
hydra/file.py
hydra/row.py
hydra/schema.py
hydra/table.py
hydradb-3.1.1.dist-info/LICENCE.txt
hydradb-3.1.1.dist-info/METADATA
hydradb-3.1.1.dist-info/WHEEL
hydradb-3.1.1.dist-info/top_level.txt
hydradb-3.1.1.dist-info/RECORD
