Metadata-Version: 2.1
Name: hydradb
Version: 3.1.1
Summary: An API for faster and easier SQLite/Python operations
Home-page: https://github.com/rhmtazad/hydraDB
Author: Rahmat Azad
Author-email: rhmtazad@gmail.com
License: MIT License
Platform: UNKNOWN
Classifier: Development Status :: 5 - Production/Stable
Classifier: Intended Audience :: Education
Classifier: License :: OSI Approved :: MIT License
Classifier: Programming Language :: Python :: 3
